{
  "db_name": "PostgreSQL",
  "query": "select id as row_id, name, country_code from public.city where country_code = any($1)",
  "describe": {
    "columns": [
      {
        "ordinal": 0,
        "name": "row_id",
        "type_info": "Int4"
      },
      {
        "ordinal": 1,
        "name": "name",
        "type_info": "Text"
      },
      {
        "ordinal": 2,
        "name": "country_code",
        "type_info": "Bpchar"
      }
    ],
    "parameters": {
      "Left": [
        "BpcharArray"
      ]
    },
    "nullable": [
      false,
      false,
      false
    ]
  },
  "hash": "e427c77493fc2f373be950f3e49d6a8d3c052043df2fec91be969ced842aeca0"
}
